goksis/__init__.py
goksis/camera.py
goksis/constants.py
goksis/enclosure.py
goksis/errors.py
goksis/filterwheel.py
goksis/focuser.py
goksis/models.py
goksis/telescope.py
goksis/utils.py
goksis/weather.py
goksis-0.0.5.dist-info/licenses/LICENSE
goksis-0.0.5.dist-info/METADATA
goksis-0.0.5.dist-info/WHEEL
goksis-0.0.5.dist-info/top_level.txt
goksis-0.0.5.dist-info/RECORD
