Metadata-Version: 2.4
Name: goksis
Version: 0.0.5
Summary: oBservatory cOntrol System aScom
Home-page: https://github.com/Turk-Astronomi-Yazilimlari/goksis
Author: Turk Astronomi Yazilimlari
License: GNU/GPL V3
Classifier: Programming Language :: Python :: 3
Classifier: Programming Language :: Python :: 3 :: Only
Classifier: Programming Language :: Python :: 3.9
Classifier: Programming Language :: Python :: 3.10
Classifier: Operating System :: OS Independent
Requires-Python: >=3.10
License-File: LICENSE
Requires-Dist: astropy
Requires-Dist: numpy
Requires-Dist: myraf
Requires-Dist: alpyca
Provides-Extra: testing
Requires-Dist: pytest>=6.0; extra == "testing"
Requires-Dist: pytest-cov>=2.0; extra == "testing"
Requires-Dist: mypy>=0.910; extra == "testing"
Requires-Dist: flake8>=3.9; extra == "testing"
Requires-Dist: tox>=3.24; extra == "testing"
Dynamic: license-file
